wgangp_pytorch/__init__.py
wgangp_pytorch/model.py
wgangp_pytorch/utils.py
wgangp_pytorch-0.1.4.dist-info/LICENSE.md
wgangp_pytorch-0.1.4.dist-info/METADATA
wgangp_pytorch-0.1.4.dist-info/WHEEL
wgangp_pytorch-0.1.4.dist-info/top_level.txt
wgangp_pytorch-0.1.4.dist-info/RECORD
