Metadata-Version: 2.1
Name: wgangp-pytorch
Version: 0.1.4
Summary: The recently proposed Wasserstein GAN (WGAN) makes progress toward stable training of GANs.
Home-page: https://github.com/Lornatang/WassersteinGAN_GP-PyTorch
Author: Liu Changyu
Author-email: liuchangyu1111@gmail.com
License: Apache
Platform: UNKNOWN
Classifier: License :: OSI Approved :: Apache Software License
Classifier: Programming Language :: Python
Classifier: Programming Language :: Python :: 3
Classifier: Programming Language :: Python :: 3.7
Requires-Python: >=3.5.0
Requires-Dist: torch
